simple_hello/__init__.py
simple_hello/main.py
echostar_public_cloud_hello-0.1.dist-info/METADATA
echostar_public_cloud_hello-0.1.dist-info/WHEEL
echostar_public_cloud_hello-0.1.dist-info/entry_points.txt
echostar_public_cloud_hello-0.1.dist-info/top_level.txt
echostar_public_cloud_hello-0.1.dist-info/RECORD
