Metadata-Version: 2.1
Name: echostar-public-cloud-hello
Version: 0.1
Summary: UNKNOWN
Home-page: UNKNOWN
License: UNKNOWN
Platform: UNKNOWN
Requires-Dist: zipp >=3.13.0
